kickerde_api_client/__init__.py
kickerde_api_client/api.py
kickerde_api_client/errors.py
kickerde_api_client/logging.py
kickerde_api_client/mapping/__init__.py
kickerde_api_client/mapping/league.py
kickerde_api_client/mapping/league_list.py
kickerde_api_client/mapping/league_season_info.py
kickerde_api_client/mapping/my_team_sync.py
kickerde_api_client/mapping/season_list.py
kickerde_api_client/mapping/team.py
kickerde_api_client/model/__init__.py
kickerde_api_client/model/association.py
kickerde_api_client/model/core.py
kickerde_api_client/model/league.py
kickerde_api_client/model/league_id.py
kickerde_api_client/model/match.py
kickerde_api_client/model/team.py
kickerde_api_client/provider.py
kickerde_api_client/settings.py
kickerde_api_client/version.py
kickerde_api_client-0.1.2.dist-info/LICENSE
kickerde_api_client-0.1.2.dist-info/METADATA
kickerde_api_client-0.1.2.dist-info/WHEEL
kickerde_api_client-0.1.2.dist-info/RECORD
