Metadata-Version: 2.1
Name: kickerde_api_client
Version: 0.1.2
Summary: Unofficial Python bindings for the public kicker.de news API
Home-page: https://github.com/claui/kickerde-api-client
License: Apache-2.0
Author: Claudia Pellegrino
Author-email: clau@tiqua.de
Requires-Python: >=3.12
Classifier: Development Status :: 3 - Alpha
Classifier: Intended Audience :: Developers
Classifier: License :: OSI Approved :: Apache Software License
Classifier: Natural Language :: German
Classifier: Programming Language :: Python :: 3
Classifier: Programming Language :: Python :: 3.12
Classifier: Programming Language :: Python :: 3.13
Classifier: Topic :: Communications
Classifier: Topic :: Home Automation
Requires-Dist: datetype
Requires-Dist: httpx (>=0.27.2,<0.28.0)
Requires-Dist: xmltodict (>=0.14.2,<0.15.0)
Project-URL: Documentation, https://kickerde-api-client.readthedocs.io/en/stable/autoapi/kickerde_api_client/
Project-URL: Repository, https://github.com/claui/kickerde-api-client
